{
  "fps": 60.0,
  "camera": {
    "fx": 384.0,
    "fy": 384.0,
    "cx": 128.0,
    "cy": 140.8,
    "camera_height_m": 1.3
  },
  "frames": [
    {
      "frame_index": 0,
      "visible": 1,
      "uv": [
        128.0,
        183.04000854492188
      ],
      "xyz": [
        0.0,
        0.20000000298023224,
        10.0
      ]
    },
    {
      "frame_index": 1,
      "visible": 1,
      "uv": [
        152.9937744140625,
        167.59823608398438
      ],
      "xyz": [
        0.698309600353241,
        0.5512751340866089,
        10.728704452514648
      ]
    },
    {
      "frame_index": 2,
      "visible": 1,
      "uv": [
        174.80828857421875,
        154.2120361328125
      ],
      "xyz": [
        1.396619200706482,
        0.8998252749443054,
        11.457409858703613
      ]
    },
    {
      "frame_index": 3,
      "visible": 1,
      "uv": [
        194.01388549804688,
        142.5126190185547
      ],
      "xyz": [
        2.094928741455078,
        1.2456504106521606,
        12.186114311218262
      ]
    },
    {
      "frame_index": 4,
      "visible": 1,
      "uv": [
        211.05215454101562,
        132.21450805664062
      ],
      "xyz": [
        2.793238401412964,
        1.5887504816055298,
        12.91481876373291
      ]
    },
    {
      "frame_index": 5,
      "visible": 1,
      "uv": [
        226.2703857421875,
        123.09312438964844
      ],
      "xyz": [
        3.4915480613708496,
        1.9291256666183472,
        13.643524169921875
      ]
    },
    {
      "frame_index": 6,
      "visible": 1,
      "uv": [
        239.9454345703125,
        114.96949768066406
      ],
      "xyz": [
        4.189857482910156,
        2.2667758464813232,
        14.372228622436523
      ]
    },
    {
      "frame_index": 7,
      "visible": 1,
      "uv": [
        252.30068969726562,
        107.69918823242188
      ],
      "xyz": [
        4.888167381286621,
        2.601700782775879,
        15.100933074951172
      ]
    },
    {
      "frame_index": 8,
      "visible": 0,
      "uv": [
        263.51837158203125,
        101.16435241699219
      ],
      "xyz": [
        5.586476802825928,
        2.933901071548462,
        15.829638481140137
      ]
    },
    {
      "frame_index": 9,
      "visible": 0,
      "uv": [
        273.7487487792969,
        95.26788330078125
      ],
      "xyz": [
        6.284786224365234,
        3.263376235961914,
        16.5583438873291
      ]
    },
    {
      "frame_index": 10,
      "visible": 0,
      "uv": [
        283.11663818359375,
        89.92906188964844
      ],
      "xyz": [
        6.983096122741699,
        3.5901262760162354,
        17.28704833984375
      ]
    },
    {
      "frame_index": 11,
      "visible": 0,
      "uv": [
        291.7266845703125,
        85.0802001953125
      ],
      "xyz": [
        7.681405544281006,
        3.914151430130005,
        18.0157527923584
      ]
    },
    {
      "frame_index": 12,
      "visible": 0,
      "uv": [
        299.66729736328125,
        80.66416931152344
      ],
      "xyz": [
        8.379714965820312,
        4.235451698303223,
        18.744457244873047
      ]
    },
    {
      "frame_index": 13,
      "visible": 0,
      "uv": [
        307.01361083984375,
        76.63239288330078
      ],
      "xyz": [
        9.078024864196777,
        4.5540266036987305,
        19.473161697387695
      ]
    },
    {
      "frame_index": 14,
      "visible": 0,
      "uv": [
        313.8299865722656,
        72.9432601928711
      ],
      "xyz": [
        9.776334762573242,
        4.869876861572266,
        20.201866149902344
      ]
    },
    {
      "frame_index": 15,
      "visible": 0,
      "uv": [
        320.17169189453125,
        69.56101989746094
      ],
      "xyz": [
        10.47464370727539,
        5.18300199508667,
        20.930572509765625
      ]
    },
    {
      "frame_index": 16,
      "visible": 0,
      "uv": [
        326.086669921875,
        66.45465850830078
      ],
      "xyz": [
        11.172953605651855,
        5.493402004241943,
        21.659276962280273
      ]
    },
    {
      "frame_index": 17,
      "visible": 0,
      "uv": [
        331.61663818359375,
        63.597251892089844
      ],
      "xyz": [
        11.87126350402832,
        5.801077365875244,
        22.387981414794922
      ]
    },
    {
      "frame_index": 18,
      "visible": 0,
      "uv": [
        336.79791259765625,
        60.96526336669922
      ],
      "xyz": [
        12.569572448730469,
        6.106027126312256,
        23.11668586730957
      ]
    },
    {
      "frame_index": 19,
      "visible": 0,
      "uv": [
        341.66253662109375,
        58.53802490234375
      ],
      "xyz": [
        13.267882347106934,
        6.408252239227295,
        23.84539031982422
      ]
    },
    {
      "frame_index": 20,
      "visible": 0,
      "uv": [
        346.2386474609375,
        56.29730987548828
      ],
      "xyz": [
        13.966192245483398,
        6.707752704620361,
        24.574094772338867
      ]
    },
    {
      "frame_index": 21,
      "visible": 0,
      "uv": [
        350.55120849609375,
        54.22703552246094
      ],
      "xyz": [
        14.664501190185547,
        7.004527568817139,
        25.30280113220215
      ]
    },
    {
      "frame_index": 22,
      "visible": 0,
      "uv": [
        354.6222839355469,
        52.312835693359375
      ],
      "xyz": [
        15.362811088562012,
        7.298577785491943,
        26.031505584716797
      ]
    },
    {
      "frame_index": 23,
      "visible": 0,
      "uv": [
        358.4716796875,
        50.542015075683594
      ],
      "xyz": [
        16.061120986938477,
        7.589902877807617,
        26.760210037231445
      ]
    }
  ]
}